detective/__init__.py
detective/__main__.py
dead_link_detective-1.0.0.dist-info/entry_points.txt
dead_link_detective-1.0.0.dist-info/WHEEL
dead_link_detective-1.0.0.dist-info/METADATA
dead_link_detective-1.0.0.dist-info/RECORD
