Metadata-Version: 2.1
Name: dead-link-detective
Version: 1.0.0
Summary: A simple asynchronous dead link detector for any website.
Author-email: Ahmed Bin Nasser <munnaa329@gmail.com>
Requires-Dist: httpx == 0.25.2
Requires-Dist: beautifulsoup4 == 4.10.0
